AutoAPI
MV2
Properties
cdat_info
cdat_lite
cdms2
cdtime
cdutil
genutil
ncml
regrid2
unidata
xmgrace
