Metadata-Version: 1.1
Name: cdat-lite
Version: 6.0.1
Summary: Core components of the Climate Data Analysis tools.  This software is based on CDAT-6.0.alpha-g82e6c52 and cdunfpp0.13.
Home-page: http://proj.badc.rl.ac.uk/cedaservices/wiki/CdatLite
Author: Ag Stephens
Author-email: ag.stephens@stfc.ac.uk
License: http://www-pcmdi.llnl.gov/software-portal/cdat/docs/cdat-license
Platform: UNKNOWN
Classifier: Development Status :: 4 - Beta
Classifier: Environment :: Console
Classifier: Intended Audience :: Science/Research
Classifier: License :: Other/Proprietary License
Classifier: Operating System :: POSIX :: Linux
Classifier: Topic :: Scientific/Engineering :: Atmospheric Science
